[
  {
    "id": "guanyu",
    "name": "关羽",
    "icon": "⚔️",
    "title": "武德双全",
    "desc": "一生忠义，武艺超群。青龙偃月刀名震天下。",
    "attrs": { "武": 95, "智": 70, "德": 90, "魅": 80 },
    "hidden": { "命运": 50, "忠义": 85 }
  },
  {
    "id": "zhugeliang",
    "name": "诸葛亮",
    "icon": "🪶",
    "title": "卧龙之智",
    "desc": "未出茅庐已知天下三分。羽扇纶巾，智冠群雄。",
    "attrs": { "武": 30, "智": 98, "德": 85, "魅": 90 },
    "hidden": { "命运": 60, "忠义": 75 }
  },
  {
    "id": "caocao",
    "name": "曹操",
    "icon": "👑",
    "title": "乱世枭雄",
    "desc": "治世之能臣，乱世之奸雄。唯才是举，志在天下。",
    "attrs": { "武": 80, "智": 92, "德": 40, "魅": 85 },
    "hidden": { "命运": 70, "忠义": 30 }
  },
  {
    "id": "zhaoyun",
    "name": "赵云",
    "icon": "🛡️",
    "title": "忠勇无双",
    "desc": "长坂坡七进七出，一身是胆。忠心耿耿，万军莫敌。",
    "attrs": { "武": 92, "智": 72, "德": 88, "魅": 75 },
    "hidden": { "命运": 45, "忠义": 80 }
  },
  {
    "id": "zhouyu",
    "name": "周瑜",
    "icon": "🔥",
    "title": "江东儒将",
    "desc": "赤壁一把火，奠定三分天下。文武兼备，风流倜傥。",
    "attrs": { "武": 75, "智": 95, "德": 65, "魅": 88 },
    "hidden": { "命运": 55, "忠义": 60 }
  },
  {
    "id": "lvbu",
    "name": "吕布",
    "icon": "💀",
    "title": "天下无双",
    "desc": "人中吕布，马中赤兔。武力天下第一，然反复无常。",
    "attrs": { "武": 99, "智": 35, "德": 20, "魅": 60 },
    "hidden": { "命运": 40, "忠义": 15 }
  }
]
